src/main.py
src/merkle_proof.py
src/util.py
dz_python_rekor_monitor-4.0.2.dist-info/METADATA
dz_python_rekor_monitor-4.0.2.dist-info/WHEEL
dz_python_rekor_monitor-4.0.2.dist-info/entry_points.txt
dz_python_rekor_monitor-4.0.2.dist-info/licenses/LICENSE
dz_python_rekor_monitor-4.0.2.dist-info/RECORD
