Metadata-Version: 2.4
Name: dz-python-rekor-monitor
Version: 4.0.2
Summary: 
License-File: LICENSE
Author: Declan Zhao
Author-email: zydc2010@gmail.com
Requires-Python: >=3.13
Classifier: Programming Language :: Python :: 3
Classifier: Programming Language :: Python :: 3.13
Classifier: Programming Language :: Python :: 3.14
Requires-Dist: autodocstring (>=0.1.2,<0.2.0)
Requires-Dist: bandit (>=1.8.6,<2.0.0)
Requires-Dist: black (>=25.9.0,<26.0.0)
Requires-Dist: cryptography (>=46.0.1,<47)
Requires-Dist: flake8 (>=7.3.0,<8.0.0)
Requires-Dist: jsonschema (>=4.25.1,<5.0.0)
Requires-Dist: mypy (>=1.18.2,<2.0.0)
Requires-Dist: pylint (>=4.0.2,<5.0.0)
Requires-Dist: pytest (>=9.0.0,<10.0.0)
Requires-Dist: pytest-cov (>=7.0.0,<8.0.0)
Requires-Dist: requests (>=2.32.5,<3)
